agents/__init__.py
agents/supervisor/__init__.py
agents/supervisor/config.py
agents/supervisor/generic_worker.py
agents/supervisor/graph.py
agents/supervisor/models.py
agents/supervisor/state.py
agents/supervisor/supervisor.py
agents/supervisor/prompts/PROMPT_GENERIC_WORKER.md
agents/supervisor/prompts/__init__.py
agents/supervisor/tools/__init__.py
agents/supervisor/tools/integration_tools.py
agents/supervisor/tools/runtime_tool_store.py
agents/supervisor/tools/spawn_worker.py
agents/supervisor/tools/think_tool.py
agents/supervisor/tools/user_context_store.py
agents/workflow_agent/__init__.py
agents/workflow_agent/agent.py
agents/workflow_agent/context.py
agents/workflow_agent/utils.py
agents/workflow_agent/tools/__init__.py
agents/workflow_agent/tools/discovery_tools.py
agents/workflow_agent/tools/workflow_tools.py
api/__init__.py
api/main.py
api/router.py
api/agents/checkpointer.py
api/agents/graphs.py
api/agents/models.py
api/agents/routes.py
api/integrations/oauth.py
api/integrations/resource_browser.py
api/integrations/router.py
api/integrations/services.py
api/middleware/auth.py
api/models/__init__.py
api/models/router.py
api/models/schema.py
api/projects/models.py
api/projects/router.py
api/projects/services.py
api/tools/__init__.py
api/tools/router.py
api/tools/services.py
api/traces/models.py
api/traces/router.py
api/traces/services.py
api/workflows/__init__.py
api/workflows/chat_schema.py
api/workflows/models.py
api/workflows/router.py
api/workflows/services.py
api/workflows/test_function_blocks.py
api/workflows/test_validation.py
cli/__init__.py
cli/main.py
seeragents-0.0.9.post1.dist-info/licenses/LICENSE
shared/__init__.py
shared/config.py
shared/llm.py
shared/logger.py
shared/database/__init__.py
shared/database/config.py
shared/database/models.py
shared/database/models_oauth.py
shared/database/workflow_models.py
shared/sandbox/__init__.py
shared/sandbox/base.py
shared/sandbox/commands.py
shared/sandbox/constants.py
shared/sandbox/deploy.py
shared/sandbox/initialize.py
shared/sandbox/tools.py
seeragents-0.0.9.post1.dist-info/METADATA
seeragents-0.0.9.post1.dist-info/WHEEL
seeragents-0.0.9.post1.dist-info/entry_points.txt
seeragents-0.0.9.post1.dist-info/top_level.txt
seeragents-0.0.9.post1.dist-info/RECORD
