Metadata-Version: 2.4
Name: seeragents
Version: 0.0.9.post1
Summary: Seer - Multi-Agent System for Evaluating AI Agents
Author-email: Lokesh Danu <lokesh@getseer.dev>, Akshay Sharma <akshay@getseer.dev>
Project-URL: Homepage, https://www.getseer.dev
Project-URL: Documentation, https://github.com/seer-engg/seer#readme
Project-URL: Repository, https://github.com/seer-engg/seer
Project-URL: Issues, https://github.com/seer-engg/seer/issues
Requires-Python: >=3.12
License-File: LICENSE
Requires-Dist: langchain>=1.1.2
Requires-Dist: langchain-openai>=1.0.2
Requires-Dist: langchain-anthropic>=1.0.0
Requires-Dist: langgraph-api==0.5.33
Requires-Dist: langgraph>=1.0.3
Requires-Dist: langgraph-cli[inmem]>=0.4.7
Requires-Dist: langgraph-checkpoint<4.0.0,>=3.0.1
Requires-Dist: langgraph-checkpoint-postgres<4.0.0,>=3.0.1
Requires-Dist: pydantic>=2.12.4
Requires-Dist: pydantic-settings>=2.0.0
Requires-Dist: httpx>=0.28.1
Requires-Dist: requests>=2.32.3
Requires-Dist: python-dotenv>=1.0.0
Requires-Dist: pyyaml>=6.0.3
Requires-Dist: e2b==2.4.0
Requires-Dist: e2b-code-interpreter==2.2.0
Requires-Dist: tavily-python>=0.7.12
Requires-Dist: langchain-chroma>=0.1.0
Requires-Dist: tenacity>=9.1.2
Requires-Dist: langchain-mcp-adapters==0.1.12
Requires-Dist: aiosqlite>=0.20.0
Requires-Dist: coolname==2.2.0
Requires-Dist: click>=8.1.0
Requires-Dist: rich>=13.0.0
Requires-Dist: asyncpg>=0.31.0
Requires-Dist: mlflow>=3.7.0
Requires-Dist: tortoise-orm[asyncpg]>=0.25.2
Requires-Dist: authlib>=1.6.6
Provides-Extra: cli
Requires-Dist: click>=8.1.0; extra == "cli"
Requires-Dist: rich>=13.0.0; extra == "cli"
Requires-Dist: python-dotenv>=1.0.0; extra == "cli"
Dynamic: license-file
